scanli.py
scanli-0.1.1.dist-info/entry_points.txt
scanli-0.1.1.dist-info/LICENSE
scanli-0.1.1.dist-info/WHEEL
scanli-0.1.1.dist-info/METADATA
scanli-0.1.1.dist-info/RECORD
